lhp/__init__.py
lhp/exceptions.py
lhp/lhp.py
lhp/models.py
lhp/py.typed
lhp/util.py
lhp-0.0.4.dist-info/LICENSE.md
lhp-0.0.4.dist-info/METADATA
lhp-0.0.4.dist-info/WHEEL
lhp-0.0.4.dist-info/RECORD
