Metadata-Version: 2.1
Name: lhp
Version: 0.0.4
Summary: Asynchronous client for the Länderübergreifendes Hochwasserportal (LHP) API.
Home-page: https://github.com/embeddedfiedel/python-lhp
License: MIT
Keywords: lhp,lhp-api,api,async,client
Author: Karsten Bade
Author-email: karsten@bade.dev
Maintainer: Karsten Bade
Maintainer-email: karsten@bade.dev
Requires-Python: >=3.8,<4.0
Classifier: Development Status :: 1 - Planning
Classifier: Intended Audience :: Developers
Classifier: License :: OSI Approved :: MIT License
Classifier: Natural Language :: English
Classifier: Programming Language :: Python :: 3
Classifier: Programming Language :: Python :: 3.8
Classifier: Programming Language :: Python :: 3.9
Classifier: Programming Language :: Python :: 3.10
Classifier: Programming Language :: Python :: 3.11
Classifier: Topic :: Software Development :: Libraries :: Python Modules
Requires-Dist: aiohttp (>=3.8.1,<4.0.0)
Requires-Dist: pydantic (>=1.8.0,<2.0.0)
Project-URL: Bug Tracker, https://github.com/embeddedfiedel/python-lhp/issues
Project-URL: Changelog, https://github.com/embeddedfiedel/python-lhp/releases
Project-URL: Documentation, https://github.com/embeddedfiedel/python-lhp
Project-URL: Repository, https://github.com/embeddedfiedel/python-lhp
